pomodoro/__init__.py
pomodoro/pomodoro.py
project_rigor_pomodoro-0.1.dist-info/licenses/LICENSE
project_rigor_pomodoro-0.1.dist-info/METADATA
project_rigor_pomodoro-0.1.dist-info/WHEEL
project_rigor_pomodoro-0.1.dist-info/top_level.txt
project_rigor_pomodoro-0.1.dist-info/RECORD
